netbox_topology_views/__init__.py
netbox_topology_views/choices.py
netbox_topology_views/filters.py
netbox_topology_views/forms.py
netbox_topology_views/models.py
netbox_topology_views/navigation.py
netbox_topology_views/search.py
netbox_topology_views/signals.py
netbox_topology_views/tables.py
netbox_topology_views/urls.py
netbox_topology_views/utils.py
netbox_topology_views/views.py
netbox_topology_views/api/__init__.py
netbox_topology_views/api/serializers.py
netbox_topology_views/api/urls.py
netbox_topology_views/api/views.py
netbox_topology_views/migrations/0001_initial.py
netbox_topology_views/migrations/0002_individualoptions.py
netbox_topology_views/migrations/0003_individualoptions_show_neighbors.py
netbox_topology_views/migrations/0004_coordinategroup_coordinate.py
netbox_topology_views/migrations/0005_individualoptions_save_coords.py
netbox_topology_views/migrations/0006_powerpanelcoordinate_powerfeedcoordinate_and_more.py
netbox_topology_views/migrations/0007_individualoptions_group_locations_and_more.py
netbox_topology_views/migrations/0008_straight_cables.py
netbox_topology_views/migrations/0009_individualoptions_group_virtualchassis.py
netbox_topology_views/migrations/0010_individualoptions_grid_size.py
netbox_topology_views/migrations/0011_individualoptions_node_label_items.py
netbox_topology_views/migrations/__init__.py
netbox_topology_views/static/netbox_topology_views/css/app.css
netbox_topology_views/static/netbox_topology_views/css/vendor.css
netbox_topology_views/static/netbox_topology_views/img/LICENSE
netbox_topology_views/static/netbox_topology_views/img/access-switch.svg
netbox_topology_views/static/netbox_topology_views/img/backhaul.svg
netbox_topology_views/static/netbox_topology_views/img/backup.svg
netbox_topology_views/static/netbox_topology_views/img/cable-doubler.svg
netbox_topology_views/static/netbox_topology_views/img/camera-server.svg
netbox_topology_views/static/netbox_topology_views/img/camera.svg
netbox_topology_views-4.5.0.dist-info/licenses/LICENSE
netbox_topology_views-4.5.0.dist-info/METADATA
netbox_topology_views-4.5.0.dist-info/WHEEL
netbox_topology_views-4.5.0.dist-info/top_level.txt
netbox_topology_views-4.5.0.dist-info/RECORD
