Metadata-Version: 2.4
Name: netbox-topology-views
Version: 4.5.0
Summary: An NetBox plugin to create Topology maps
Home-page: https://github.com/mattieserver/netbox-topology-views
Author: Mattijs Vanhaverbeke
License: Apache 2.0
Project-URL: Source, https://github.com/mattieserver/netbox-topology-views
Keywords: netbox-plugin
Classifier: Programming Language :: Python
Classifier: Programming Language :: Python :: 3
Classifier: Programming Language :: Python :: 3 :: Only
License-File: LICENSE
Dynamic: author
Dynamic: classifier
Dynamic: description
Dynamic: description-content-type
Dynamic: home-page
Dynamic: keywords
Dynamic: license
Dynamic: license-file
Dynamic: project-url
Dynamic: summary
